check_dht/__init__.py
check_dht/__main__.py
check_dht/dht.py
check_dht-0.1.5.dist-info/LICENSE
check_dht-0.1.5.dist-info/METADATA
check_dht-0.1.5.dist-info/WHEEL
check_dht-0.1.5.dist-info/entry_points.txt
check_dht-0.1.5.dist-info/RECORD
