Metadata-Version: 2.1
Name: check-dht
Version: 0.1.5
Summary: Nagios plugin to monitor humidity and temperature data from a Raspberry Pi Pico
Home-page: https://github.com/j0hax/check-dht
License: GPL-3.0-or-later
Keywords: nagios,monitoring
Author: Johannes Arnold
Author-email: johannes.arnold@stud.uni-hannover.de
Requires-Python: >=3.6,<4.0
Classifier: License :: OSI Approved :: GNU General Public License v3 or later (GPLv3+)
Classifier: Programming Language :: Python :: 3
Classifier: Programming Language :: Python :: 3.6
Classifier: Programming Language :: Python :: 3.7
Classifier: Programming Language :: Python :: 3.8
Classifier: Programming Language :: Python :: 3.9
Classifier: Programming Language :: Python :: 3.10
Classifier: Programming Language :: Python :: 3.11
Requires-Dist: nagiosplugin (>=1.3.3,<2.0.0)
Requires-Dist: pyserial (>=3.5,<4.0)
Project-URL: Repository, https://github.com/j0hax/check-dht
